Outlier_Removal_UsingIQR_101883059_pkg/Outlier_Removal_UsingIQR.py
Outlier_Removal_UsingIQR_101883059_pkg/__init__.py
Outlier_Removal_UsingIQR_101883059_Priyanshu_Tuli-0.0.1.dist-info/LICENSE
Outlier_Removal_UsingIQR_101883059_Priyanshu_Tuli-0.0.1.dist-info/METADATA
Outlier_Removal_UsingIQR_101883059_Priyanshu_Tuli-0.0.1.dist-info/WHEEL
Outlier_Removal_UsingIQR_101883059_Priyanshu_Tuli-0.0.1.dist-info/top_level.txt
Outlier_Removal_UsingIQR_101883059_Priyanshu_Tuli-0.0.1.dist-info/RECORD
