Metadata-Version: 2.1
Name: Outlier-Removal-UsingIQR-101883059-Priyanshu-Tuli
Version: 0.0.1
Summary: A package for removing the outliers from a dataset using inter quartile range(IQR)
Home-page: https://github.com/Priyanshu0/Outlier_Removal_Using_IQR
Author: Priyanshu Tuli
Author-email: priyanshu1tuli@gmail.com
License: UNKNOWN
Platform: UNKNOWN
Classifier: Programming Language :: Python :: 3
Classifier: License :: OSI Approved :: MIT License
Classifier: Operating System :: OS Independent
Requires-Python: >=3.6
